CHANGES.rst
DESCRIPTION.rst
LICENSE
MANIFEST.in
README.md
setup.py
src/ldc_faster_whisper/__init__.py
src/ldc_faster_whisper/class_lister.py
src/ldc_faster_whisper.egg-info/PKG-INFO
src/ldc_faster_whisper.egg-info/SOURCES.txt
src/ldc_faster_whisper.egg-info/dependency_links.txt
src/ldc_faster_whisper.egg-info/entry_points.txt
src/ldc_faster_whisper.egg-info/requires.txt
src/ldc_faster_whisper.egg-info/top_level.txt
src/ldc_faster_whisper/pretrain/__init__.py
src/ldc_faster_whisper/pretrain/_fw_audio.py