Metadata-Version: 2.1
Name: ldc-faster-whisper
Version: 0.0.3
Summary: Python3 library that adds audio transcription support (.wav, .mp3) to the llm-dataset-converter library.
Home-page: https://github.com/waikato-llm/ldc-faster-whisper
Author: Peter Reutemann
Author-email: fracpete@waikato.ac.nz
License: MIT License
Classifier: Development Status :: 4 - Beta
Classifier: License :: OSI Approved :: MIT License
Classifier: Topic :: Scientific/Engineering :: Artificial Intelligence
Classifier: Programming Language :: Python :: 3
License-File: LICENSE
